{
  "title": "CCE20250924_0022",
  "source_file": "/home/runner/work/ad-res-j7/ad-res-j7/ANNEXURES/JF07/CCE20250924_0022.jpg",
  "created_at": "2025-10-21T22:01:01.062Z",
  "file_type": "markdown",
  "generated_via": "ocr",
  "sections": [
    {
      "heading": "OCR Content",
      "level": 2,
      "content": "Re\n\n14/8/2025-8:16:25 AM\n\n_T have, with respect, the necessary focus standi to bring this application, as con-\n\nfemplated in Section 182(2) of the Companies Act, No 71 of 2008 (the “Compa.\n\nnies Act), in that | am a director and shareholder of the third respondent, and 1\n\nam a member of the third, fourth, fifth, and sixth respondents.\n\n6.1\n\n6.2\n\n6.3\n\n6.4\n\n6.5\n\nMy wife is a director of the third respondent, and a member of the fourth,\n\nfifth, and sixth respondents,\n\nMy son is a director of the third respondent, and a member of the sixth\n\nrespondent,\n\n| caused the third to sixth respondent to be created, together with their\n\npresent directors/members.\n\nThe third to sixth respondents bank with the seventh and eighth re-\n\nspondents.\n\nThe third to sixth respondents are registered with the ninth respondent.\n\nWV\n\nPage 7/29\n\nPage 15 of 37",
      "subsections": []
    }
  ]
}